{
  "id": 795,
  "surahNumber": "006",
  "ayatNumber": "006",
  "arabic": "أَلَمْ يَرَوْا كَمْ أَهْلَكْنَا مِنْ قَبْلِهِمْ مِنْ قَرْنٍ مَكَّنَّاهُمْ فِي الْأَرْضِ مَا لَمْ نُمَكِّنْ لَكُمْ وَأَرْسَلْنَا السَّمَاءَ عَلَيْهِمْ مِدْرَارًا وَجَعَلْنَا الْأَنْهَارَ تَجْرِي مِنْ تَحْتِهِمْ فَأَهْلَكْنَاهُمْ بِذُنُوبِهِمْ وَأَنْشَأْنَا مِنْ بَعْدِهِمْ قَرْنًا آخَرِينَ",
  "english": "Have they not seen how many a generation before them We have destroyed whom We had established on the earth such as We have not established you? And We poured out on them rain from the sky in abundance, and made the rivers flow under them. Yet We destroyed them for their sins, and created after them other generations.",
  "bengali": "তারা কি দেখেনি যে, আমি তাদের পুর্বে কত সম্প্রদায়কে ধ্বংস করে দিয়েছি, যাদেরকে আমি পৃথিবীতে এমন প্রতিষ্ঠা দিয়েছিলাম, যা তোমাদেরকে দেইনি। আমি আকাশকে তাদের উপর অনবরত বৃষ্টি বর্ষণ করতে দিয়েছি এবং তাদের তলদেশে নদী সৃষ্টি করে দিয়েছি, অতঃপর আমি তাদেরকে তাদের পাপের কারণে ধ্বংস করে দিয়েছি এবং তাদের পরে অন্য সম্প্রদায় সৃষ্টি করেছি।"
}
