{
  "id": 537,
  "surahNumber": "004",
  "ayatNumber": "044",
  "arabic": "أَلَمْ تَرَ إِلَى الَّذِينَ أُوتُوا نَصِيبًا مِنَ الْكِتَابِ يَشْتَرُونَ الضَّلَالَةَ وَيُرِيدُونَ أَنْ تَضِلُّوا السَّبِيلَ",
  "english": "Have you not seen those who were given a portion of the book (the Jews), purchasing the wrong path, and wish that you should go astray from the Right Path?",
  "bengali": "তুমি কি ওদের দেখনি, যারা কিতাবের কিছু অংশ প্রাপ্ত হয়েছে, (অথচ) তারা পথভ্রষ্টতা খরিদ করে এবং কামনা করে, যাতে তোমরাও আল্লাহর পথ থেকে বিভ্রান্ত হয়ে যাও।"
}
