{
  "id": 512,
  "surahNumber": "004",
  "ayatNumber": "019",
  "arabic": "يَا أَيُّهَا الَّذِينَ آمَنُوا لَا يَحِلُّ لَكُمْ أَنْ تَرِثُوا النِّسَاءَ كَرْهًا ۖ وَلَا تَعْضُلُوهُنَّ لِتَذْهَبُوا بِبَعْضِ مَا آتَيْتُمُوهُنَّ إِلَّا أَنْ يَأْتِينَ بِفَاحِشَةٍ مُبَيِّنَةٍ ۚ وَعَاشِرُوهُنَّ بِالْمَعْرُوفِ ۚ فَإِنْ كَرِهْتُمُوهُنَّ فَعَسَىٰ أَنْ تَكْرَهُوا شَيْئًا وَيَجْعَلَ اللَّهُ فِيهِ خَيْرًا كَثِيرًا",
  "english": "O you who believe! You are forbidden to inherit women against their will, and you should not treat them with harshness, that you may take away part of the Mahr you have given them, unless they commit open illegal sexual intercourse. And live with them honourably. If you dislike them, it may be that you dislike a thing and Allah brings through it a great deal of good.",
  "bengali": "হে ঈমাণদারগণ! বলপূর্বক নারীদেরকে উত্তরাধিকারে গ্রহন করা তোমাদের জন্যে হালাল নয় এবং তাদেরকে আটক রেখো না যাতে তোমরা তাদেরকে যা প্রদান করেছ তার কিয়দংশ নিয়ে নাও; কিন্তু তারা যদি কোন প্রকাশ্য অশ্লীলতা করে! নারীদের সাথে সদ্ভাবে জীবন-যাপন কর। অতঃপর যদি তাদেরকে অপছন্দ কর, তবে হয়ত তোমরা এমন এক জিনিসকে অপছন্দ করছ, যাতে আল্লাহ, অনেক কল্যাণ রেখেছেন।"
}
