{
  "id": 156,
  "surahNumber": "002",
  "ayatNumber": "149",
  "arabic": "وَمِنْ حَيْثُ خَرَجْتَ فَوَلِّ وَجْهَكَ شَطْرَ الْمَسْجِدِ الْحَرَامِ ۖ وَإِنَّهُ لَلْحَقُّ مِنْ رَبِّكَ ۗ وَمَا اللَّهُ بِغَافِلٍ عَمَّا تَعْمَلُونَ",
  "english": "And from wheresoever you start forth (for prayers), turn your face in the direction of Al-Masjid-al-Haram (at Makkah), that is indeed the truth from your Lord. And Allah is not unaware of what you do.",
  "bengali": "আর যে স্থান থেকে তুমি বের হও, নিজের মুখ মসজিদে হারামের দিকে ফেরাও-নিঃসন্দেহে এটাই হলো তোমার পালনকর্তার পক্ষ থেকে নির্ধারিত বাস্তব সত্য। বস্তুতঃ তোমার পালনকর্তা তোমাদের কার্যকলাপ সম্পর্কে অনবহিত নন।"
}
