{
  "id": 142,
  "surahNumber": "002",
  "ayatNumber": "135",
  "arabic": "وَقَالُوا كُونُوا هُودًا أَوْ نَصَارَىٰ تَهْتَدُوا ۗ قُلْ بَلْ مِلَّةَ إِبْرَاهِيمَ حَنِيفًا ۖ وَمَا كَانَ مِنَ الْمُشْرِكِينَ",
  "english": "And they say, \"Be Jews or Christians, then you will be guided.\" Say (to them, O Muhammad Peace be upon him), \"Nay, (We follow) only the religion of Ibrahim (Abraham), Hanifa [Islamic Monotheism, i.e. to worship none but Allah (Alone)], and he was not of Al-Mushrikun (those who worshipped others along with Allah - see V. 2:105).\"",
  "bengali": "তারা বলে, তোমরা ইহুদী অথবা খ্রীষ্টান হয়ে যাও, তবেই সুপথ পাবে। আপনি বলুন, কখনই নয়; বরং আমরা ইব্রাহীমের ধর্মে আছি যাতে বক্রতা নেই। সে মুশরিকদের অন্তর্ভুক্ত ছিল না।"
}
