{
  "id": 4094,
  "surahNumber": "039",
  "ayatNumber": "036",
  "arabic": "أَلَيْسَ اللَّهُ بِكَافٍ عَبْدَهُ ۖ وَيُخَوِّفُونَكَ بِالَّذِينَ مِنْ دُونِهِ ۚ وَمَنْ يُضْلِلِ اللَّهُ فَمَا لَهُ مِنْ هَادٍ",
  "english": "Is not Allah Sufficient for His slave? Yet they try to frighten you with those (whom they worship) besides Him! And whom Allah sends astray, for him there will be no guide.",
  "bengali": "আল্লাহ কি তাঁর বান্দার পক্ষে যথেষ্ট নন? অথচ তারা আপনাকে আল্লাহর পরিবর্তে অন্যান্য উপাস্যদের ভয় দেখায়। আল্লাহ যাকে গোমরাহ করেন, তার কোন পথপ্রদর্শক নেই।"
}
