{
  "id": 3571,
  "surahNumber": "033",
  "ayatNumber": "038",
  "arabic": "مَا كَانَ عَلَى النَّبِيِّ مِنْ حَرَجٍ فِيمَا فَرَضَ اللَّهُ لَهُ ۖ سُنَّةَ اللَّهِ فِي الَّذِينَ خَلَوْا مِنْ قَبْلُ ۚ وَكَانَ أَمْرُ اللَّهِ قَدَرًا مَقْدُورًا",
  "english": "There is no blame on the Prophet (SAW) in that which Allah has made legal for him. That has been Allah's Way with those who have passed away of (the Prophets of) old. And the Command of Allah is a decree determined.",
  "bengali": "আল্লাহ নবীর জন্যে যা নির্ধারণ করেন, তাতে তাঁর কোন বাধা নেই পূর্ববর্তী নবীগণের ক্ষেত্রে এটাই ছিল আল্লাহর চিরাচরিত বিধান। আল্লাহর আদেশ নির্ধারিত, অবধারিত।"
}
