{
  "id": 1399,
  "surahNumber": "010",
  "ayatNumber": "035",
  "arabic": "قُلْ هَلْ مِنْ شُرَكَائِكُمْ مَنْ يَهْدِي إِلَى الْحَقِّ ۚ قُلِ اللَّهُ يَهْدِي لِلْحَقِّ ۗ أَفَمَنْ يَهْدِي إِلَى الْحَقِّ أَحَقُّ أَنْ يُتَّبَعَ أَمَّنْ لَا يَهِدِّي إِلَّا أَنْ يُهْدَىٰ ۖ فَمَا لَكُمْ كَيْفَ تَحْكُمُونَ",
  "english": "Say: \"Is there of your (Allah's so-called) partners one that guides to the truth?\" Say: \"It is Allah Who guides to the truth. Is then He, Who gives guidance to the truth, more worthy to be followed, or he who finds not guidance (himself) unless he is guided? Then, what is the matter with you? How judge you?\"",
  "bengali": "জিজ্ঞেস কর, আছে কি কেউ তোমাদের শরীকদের মধ্যে যে সত্য-সঠিক পথ প্রদর্শন করবে? বল, আল্লাহই সত্য-সঠিক পথ প্রদর্শন করেন, সুতরাং এমন যে লোক সঠিক পথ দেখাবে তার কথা মান্য করা কিংবা যে লোক নিজে নিজে পথ খুঁজে পায় না, তাকে পথ দেখানো কর্তব্য। অতএব, তোমাদের কি হল, কেমন তোমাদের বিচার?"
}
