{
  "id": 4193,
  "surahNumber": "040",
  "ayatNumber": "060",
  "arabic": "وَقَالَ رَبُّكُمُ ادْعُونِي أَسْتَجِبْ لَكُمْ ۚ إِنَّ الَّذِينَ يَسْتَكْبِرُونَ عَنْ عِبَادَتِي سَيَدْخُلُونَ جَهَنَّمَ دَاخِرِينَ",
  "english": "And your Lord said: \"Invoke Me, [i.e. believe in My Oneness (Islamic Monotheism)] (and ask Me for anything) I will respond to your (invocation). Verily! Those who scorn My worship [i.e. do not invoke Me, and do not believe in My Oneness, (Islamic Monotheism)] they will surely enter Hell in humiliation!\"",
  "bengali": "তোমাদের পালনকর্তা বলেন, তোমরা আমাকে ডাক, আমি সাড়া দেব। যারা আমার এবাদতে অহংকার করে তারা সত্বরই জাহান্নামে দাখিল হবে লাঞ্ছিত হয়ে।"
}
