{
  "id": 686,
  "surahNumber": "005",
  "ayatNumber": "017",
  "arabic": "لَقَدْ كَفَرَ الَّذِينَ قَالُوا إِنَّ اللَّهَ هُوَ الْمَسِيحُ ابْنُ مَرْيَمَ ۚ قُلْ فَمَنْ يَمْلِكُ مِنَ اللَّهِ شَيْئًا إِنْ أَرَادَ أَنْ يُهْلِكَ الْمَسِيحَ ابْنَ مَرْيَمَ وَأُمَّهُ وَمَنْ فِي الْأَرْضِ جَمِيعًا ۗ وَلِلَّهِ مُلْكُ السَّمَاوَاتِ وَالْأَرْضِ وَمَا بَيْنَهُمَا ۚ يَخْلُقُ مَا يَشَاءُ ۚ وَاللَّهُ عَلَىٰ كُلِّ شَيْءٍ قَدِيرٌ",
  "english": "Surely, in disbelief are they who say that Allah is the Messiah, son of Maryam (Mary). Say (O Muhammad SAW): \"Who then has the least power against Allah, if He were to destroy the Messiah, son of Maryam (Mary), his mother, and all those who are on the earth together?\" And to Allah belongs the dominion of the heavens and the earth, and all that is between them. He creates what He wills. And Allah is Able to do all things.",
  "bengali": "নিশ্চয় তারা কাফের, যারা বলে, মসীহ ইবনে মরিয়মই আল্লাহ। আপনি জিজ্ঞেস করুন, যদি তাই হয়, তবে বল যদি আল্লাহ মসীহ ইবনে মরিয়ম, তাঁর জননী এবং ভূমন্ডলে যারা আছে, তাদের সবাইকে ধ্বংস করতে চান, তবে এমন কারও সাধ্য আছে কি যে আল্লাহর কাছ থেকে তাদেরকে বিন্দুমাত্রও বাঁচাতে পারে? নভোমন্ডল, ভুমন্ডল ও এতদুভয়ের মধ্যে যা আছে, সবকিছুর উপর আল্লাহ তা’আলার আধিপত্য। তিনি যা ইচ্ছা সৃষ্টি করেন। আল্লাহ সবকিছুর উপর শক্তিমান।"
}
