{
  "id": 335,
  "surahNumber": "003",
  "ayatNumber": "042",
  "arabic": "وَإِذْ قَالَتِ الْمَلَائِكَةُ يَا مَرْيَمُ إِنَّ اللَّهَ اصْطَفَاكِ وَطَهَّرَكِ وَاصْطَفَاكِ عَلَىٰ نِسَاءِ الْعَالَمِينَ",
  "english": "And (remember) when the angels said: \"O Maryam (Mary)! Verily, Allah has chosen you, purified you (from polytheism and disbelief), and chosen you above the women of the 'Alamin (mankind and jinns) (of her lifetime).\"",
  "bengali": "আর যখন ফেরেশতা বলল হে মারইয়াম!, আল্লাহ তোমাকে পছন্দ করেছেন এবং তোমাকে পবিত্র পরিচ্ছন্ন করে দিয়েছেন। আর তোমাকে বিশ্ব নারী সমাজের উর্ধ্বে মনোনীত করেছেন।"
}
