{
  "id": 444,
  "surahNumber": "003",
  "ayatNumber": "151",
  "arabic": "سَنُلْقِي فِي قُلُوبِ الَّذِينَ كَفَرُوا الرُّعْبَ بِمَا أَشْرَكُوا بِاللَّهِ مَا لَمْ يُنَزِّلْ بِهِ سُلْطَانًا ۖ وَمَأْوَاهُمُ النَّارُ ۚ وَبِئْسَ مَثْوَى الظَّالِمِينَ",
  "english": "We shall cast terror into the hearts of those who disbelieve, because they joined others in worship with Allah, for which He had sent no authority; their abode will be the Fire and how evil is the abode of the Zalimun (polytheists and wrong-doers).",
  "bengali": "খুব শীঘ্রই আমি কাফেরদের মনে ভীতির সঞ্চার করবো। কারণ, ওরা আল্লাহর সাথে অংশীদার সাব্যস্ত করে যে সম্পর্কে কোন সনদ অবতীর্ণ করা হয়নি। আর ওদের ঠিকানা হলো দোযখের আগুন। বস্তুতঃ জালেমদের ঠিকানা অত্যন্ত নিকৃষ্ট।"
}
