{
  "id": 4376,
  "surahNumber": "043",
  "ayatNumber": "051",
  "arabic": "وَنَادَىٰ فِرْعَوْنُ فِي قَوْمِهِ قَالَ يَا قَوْمِ أَلَيْسَ لِي مُلْكُ مِصْرَ وَهَٰذِهِ الْأَنْهَارُ تَجْرِي مِنْ تَحْتِي ۖ أَفَلَا تُبْصِرُونَ",
  "english": "And Fir'aun (Pharaoh) proclaimed among his people, saying: \"O my people! Is not mine the dominion of Egypt, and these rivers flowing underneath me. See you not then?",
  "bengali": "ফেরাউন তার সম্প্রদায়কে ডেকে বলল, হে আমার কওম, আমি কি মিসরের অধিপতি নই? এই নদী গুলো আমার নিম্নদেশে প্রবাহিত হয়, তোমরা কি দেখ না?"
}
