{
  "id": 1737,
  "surahNumber": "013",
  "ayatNumber": "030",
  "arabic": "كَذَٰلِكَ أَرْسَلْنَاكَ فِي أُمَّةٍ قَدْ خَلَتْ مِنْ قَبْلِهَا أُمَمٌ لِتَتْلُوَ عَلَيْهِمُ الَّذِي أَوْحَيْنَا إِلَيْكَ وَهُمْ يَكْفُرُونَ بِالرَّحْمَٰنِ ۚ قُلْ هُوَ رَبِّي لَا إِلَٰهَ إِلَّا هُوَ عَلَيْهِ تَوَكَّلْتُ وَإِلَيْهِ مَتَابِ",
  "english": "Thus have We sent you (O Muhammad SAW) to a community before whom other communities have passed away, in order that you might recite unto them what We have inspired to you, while they disbelieve in the Most Beneficient (Allah) Say: \"He is my Lord! La ilaha illa Huwa (none has the right to be worshipped but He)! In Him is my trust, and to Him will be my return with repentance.\"",
  "bengali": "এমনিভাবে আমি আপনাকে একটি উম্মতের মধ্যে প্রেরণ করেছি। তাদের পূর্বে অনেক উম্মত অতিক্রান্ত হয়েছে। যাতে আপনি তাদেরকে ঐ নির্দেশ শুনিয়ে দেন, যা আমি আপনার কাছে প্রেরণ করেছি। তথাপি তারা দয়াময়কে অস্বীকার করে। বলুনঃ তিনিই আমার পালনকর্তা। তিনি ব্যতীত কারও উপাসনা নাই। আমি তাঁর উপরই ভরসা করেছি এবং তাঁর দিকেই আমার প্রত্যাবর্তণ।"
}
