{
  "id": 1604,
  "surahNumber": "012",
  "ayatNumber": "008",
  "arabic": "إِذْ قَالُوا لَيُوسُفُ وَأَخُوهُ أَحَبُّ إِلَىٰ أَبِينَا مِنَّا وَنَحْنُ عُصْبَةٌ إِنَّ أَبَانَا لَفِي ضَلَالٍ مُبِينٍ",
  "english": "When they said: \"Truly, Yusuf (Joseph) and his brother (Benjamin) are loved more by our father than we, but we are 'Usbah (a strong group). Really, our father is in a plain error.",
  "bengali": "যখন তারা বললঃ অবশ্যই ইউসুফ ও তাঁর ভাই আমাদের পিতার কাছে আমাদের চাইতে অধিক প্রিয় অথচ আমরা একটা সংহত শক্তি বিশেষ। নিশ্চয় আমাদের পিতা স্পষ্ট ভ্রান্তিতে রয়েছেন।"
}
