{
  "id": 2234,
  "surahNumber": "018",
  "ayatNumber": "094",
  "arabic": "قَالُوا يَا ذَا الْقَرْنَيْنِ إِنَّ يَأْجُوجَ وَمَأْجُوجَ مُفْسِدُونَ فِي الْأَرْضِ فَهَلْ نَجْعَلُ لَكَ خَرْجًا عَلَىٰ أَنْ تَجْعَلَ بَيْنَنَا وَبَيْنَهُمْ سَدًّا",
  "english": "They said: \"O Dhul-Qarnain! Verily! Ya'juj and Ma'juj (Gog and Magog) are doing great mischief in the land. Shall we then pay you a tribute in order that you might erect a barrier between us and them?\"",
  "bengali": "তারা বললঃ হে যুলকারনাইন, ইয়াজুজ ও মাজুজ দেশে অশান্তি সৃষ্টি করেছে। আপনি বললে আমরা আপনার জন্যে কিছু কর ধার্য করব এই শর্তে যে, আপনি আমাদের ও তাদের মধ্যে একটি প্রাচীর নির্মাণ করে দেবেন।"
}
